AUTHORS
CHANGELOG.rst
LICENSE
MANIFEST.in
README.rst
setup.py
cyipopt/__init__.py
cyipopt/ipopt_wrapper.py
cyipopt/scipy_interface.py
cyipopt/utils.py
cyipopt/version.py
cyipopt/cython/ipopt.pxd
cyipopt/cython/ipopt_wrapper.pyx
cyipopt/tests/__init__.py
cyipopt/tests/conftest.py
cyipopt/tests/integration/__init__.py
cyipopt/tests/integration/test_hs071.py
cyipopt/tests/integration/test_lasso.py
cyipopt/tests/integration/test_rosen.py
cyipopt/tests/unit/__init__.py
cyipopt/tests/unit/test_defaults.py
cyipopt/tests/unit/test_deprecations.py
cyipopt/tests/unit/test_errors.py
cyipopt/tests/unit/test_exceptions.py
cyipopt/tests/unit/test_ipopt_funcs.py
cyipopt/tests/unit/test_options.py
cyipopt/tests/unit/test_scipy_optional.py
docs/Makefile
docs/make.bat
docs/source/conf.py
docs/source/development.rst
docs/source/index.rst
docs/source/install.rst
docs/source/reference.rst
docs/source/tutorial.rst
ipopt/__init__.py
ipopt.egg-info/PKG-INFO
ipopt.egg-info/SOURCES.txt
ipopt.egg-info/dependency_links.txt
ipopt.egg-info/not-zip-safe
ipopt.egg-info/requires.txt
ipopt.egg-info/top_level.txt