Metadata-Version: 1.1
Name: ipopt
Version: 1.0.3
Summary: A Cython wrapper to the IPOPT optimization package
Home-page: https://github.com/mechmotum/cyipopt
Author: Jason K. Moore
Author-email: moorepants@gmail.com
License: EPL-1.0
Keywords: coin-or,interior-point,ipopt,nlp,nonlinear programming,optimization
Platform: UNKNOWN
Classifier: Development Status :: 5 - Production/Stable
Classifier: License :: OSI Approved :: Eclipse Public License 1.0 (EPL-1.0)
Classifier: Intended Audience :: Science/Research
Classifier: Operating System :: OS Independent
Classifier: Programming Language :: Python :: 3.6
Classifier: Programming Language :: Python :: 3.7
Classifier: Programming Language :: Python :: 3.8
Classifier: Programming Language :: Python :: 3.9
